CMakeLists.txt
LICENSE
README.md
pyproject.toml
setup.py
sort/__init__.py
sort/include/kalman_filter.h
sort/include/matrix.cpp
sort/include/matrix.h
sort/include/munkres.h
sort/include/track.h
sort/include/tracker.h
sort/include/utils.h
sort/src/Py_SORT.cpp
sort/src/kalman_filter.cpp
sort/src/munkres.cpp
sort/src/track.cpp
sort/src/tracker.cpp
sort_tracker.egg-info/PKG-INFO
sort_tracker.egg-info/SOURCES.txt
sort_tracker.egg-info/dependency_links.txt
sort_tracker.egg-info/requires.txt
sort_tracker.egg-info/top_level.txt