Metadata-Version: 2.1
Name: sort-tracker
Version: 1.0.5
Summary: SORT tracker
Home-page: https://github.com/MrGolden1/sort-python
Author: M.Ali Zarrinzade
Author-email: ali.zarrinzadeh@gmail.com
License: GPL-3.0
Project-URL: Bug Tracker, https://github.com/MrGolden1/sort-python/issues
Platform: UNKNOWN
Classifier: Development Status :: 5 - Production/Stable
Classifier: Intended Audience :: Developers
Classifier: Intended Audience :: Science/Research
Classifier: Programming Language :: Python :: 3
